Workbook

Sheet 📊 Dashboard
A1: WealthPilot 360 — Financial Dashboard
A2: Personal CFO · Auto-Summary from all sheets
A4: KEY PERFORMANCE INDICATORS
A5: 💎 Net Worth | D5: 📈 Total Investments | G5: 🏦 Total Loan O/S
A6: =SUM('💰 Assets'!C:C)-SUM('💰 Assets'!D:D)-SUM('🏦 Loans'!E:E) | D6: =SUM('📈 Investments'!D:D) | G6: =SUM('🏦 Loans'!E:E)
A8: 📋 Monthly EMI | D8: 🛡️ Insurance Premium | G8: 💳 CC Outstanding
A9: =SUM('🏦 Loans'!F:F) | D9: =SUM('🛡️ Insurance'!D:D) | G9: =SUM('💳 Credit Cards'!D:D)
A12: ℹ️ All values above auto-calculate from the data sheets. Fill in each sheet below to update this dashboard.

Sheet 👤 Users
A1: WealthPilot 360 — User Registry
A2: All registered users & account details
A4: User ID | B4: Full Name | C4: Mobile | D4: Email | E4: Password (hashed) | F4: Registered On | G4: Last Login | H4: Plan
A5: suman123 | B5: Suman | C5: 9832014403 | D5: suman@example.com | E5: •••••••• | F5: 28-Jun-2026 | G5: 28-Jun-2026 | H5: Premium

Sheet 🏦 Loans
A1: WealthPilot 360 — Loans & EMI Tracker
A2: Track all home, car, personal & other loans
A4: Loan Name | B4: Bank / Lender | C4: Loan Type | D4: Original Amount (₹) | E4: Outstanding (₹) | F4: Monthly EMI (₹) | G4: Interest Rate (%) | H4: EMI Due Date | I4: User ID | J4: Notes
A5: Home Loan | B5: SBI | C5: Home Loan | D5: 4500000 | E5: 3200000 | F5: 38000 | G5: 8.5 | H5: 2026-07-05 | I5: suman123
A6: Car Loan | B6: HDFC | C6: Car Loan | D6: 800000 | E6: 350000 | F6: 17500 | G6: 9.2 | H6: 2026-07-12 | I6: suman123
A7: TOTAL | D7: =SUM(D5:D6) | E7: =SUM(E5:E6) | F7: =SUM(F5:F6)

Sheet 📋 Bills
A1: WealthPilot 360 — Bills & Dues
A2: Electricity, broadband, mobile & all recurring bills
A4: Bill Name | B4: Provider | C4: Category | D4: Amount (₹) | E4: Due Date | F4: Status | G4: User ID | H4: Notes
A5: Electricity Bill | B5: CESC | C5: Electricity | D5: 2800 | E5: 2026-07-01 | F5: Pending | G5: suman123
A6: Broadband | B6: JioFiber | C6: Broadband | D6: 999 | E6: 2026-07-06 | F6: Pending | G6: suman123
A7: Mobile Recharge | B7: Jio | C7: Mobile | D7: 479 | E7: 2026-07-04 | F7: Pending | G7: suman123
A8: TOTAL | D8: =SUM(D5:D7)

Sheet 🛡️ Insurance
A1: WealthPilot 360 — Insurance Policies
A2: Life, health, motor & all insurance policies
A4: Policy Name | B4: Type | C4: Policy Number | D4: Annual Premium (₹) | E4: Renewal Date | F4: Coverage (₹) | G4: Nominee | H4: User ID | I4: Notes
A5: LIC Jeevan Anand | B5: Life Insurance | C5: LIC234567 | D5: 28000 | E5: 2026-08-12 | F5: 5000000 | G5: Spouse | H5: suman123
A6: Star Health Family | B6: Health Insurance | C6: SH89012 | D6: 22000 | E6: 2026-09-26 | F6: 1000000 | G6: Family | H6: suman123
A7: HDFC ERGO Car | B7: Motor Insurance | C7: HE45678 | D7: 12000 | E7: 2026-10-26 | F7: 600000 | H7: suman123
A8: TOTAL | D8: =SUM(D5:D7) | F8: =SUM(F5:F7)

Sheet 📈 Investments
A1: WealthPilot 360 — Investments
A2: Mutual Funds, SIP, Gold, PPF & all investments
A4: Investment Name | B4: Type | C4: Invested Amount (₹) | D4: Current Value (₹) | E4: Gain/Loss (₹) | F4: Return (%) | G4: User ID | H4: Notes
A5: SBI Bluechip Fund | B5: Mutual Fund | C5: 200000 | D5: 248000 | E5: =D5-C5 | F5: =IF(C5>0,(D5-C5)/C5,0) | G5: suman123
A6: HDFC SIP | B6: SIP | C6: 120000 | D6: 138500 | E6: =D6-C6 | F6: =IF(C6>0,(D6-C6)/C6,0) | G6: suman123
A7: Sovereign Gold Bond | B7: Gold | C7: 50000 | D7: 61000 | E7: =D7-C7 | F7: =IF(C7>0,(D7-C7)/C7,0) | G7: suman123
A8: PPF Account | B8: PPF | C8: 150000 | D8: 168000 | E8: =D8-C8 | F8: =IF(C8>0,(D8-C8)/C8,0) | G8: suman123
A9: TOTAL | C9: =SUM(C5:C8) | D9: =SUM(D5:D8) | E9: =SUM(E5:E8)

Sheet 💰 Assets
A1: WealthPilot 360 — Assets & Liabilities
A2: Net Worth breakdown — what you own vs what you owe
A4: Name | B4: Type (Asset/Liability) | C4: Asset Value (₹) | D4: Liability Value (₹) | E4: User ID | F4: Notes
A5: Apartment (2BHK) | B5: Asset | C5: 7500000 | D5: 0 | E5: suman123
A6: Savings Account | B6: Asset | C6: 350000 | D6: 0 | E6: suman123
A7: FD – SBI | B7: Asset | C7: 500000 | D7: 0 | E7: suman123
A8: Personal Loan | B8: Liability | C8: 0 | D8: 150000 | E8: suman123
A9: TOTAL | C9: =SUM(C5:C8) | D9: =SUM(D5:D8)
A10: NET WORTH (Assets − Liabilities) | C10: =C9-D9

Sheet 💳 Credit Cards
A1: WealthPilot 360 — Credit Card Manager
A2: All credit cards, limits, outstanding & due dates
A4: Card Name | B4: Bank | C4: Credit Limit (₹) | D4: Outstanding (₹) | E4: Min Due (₹) | F4: Payment Due Date | G4: Utilization (%) | H4: User ID
A5: HDFC Millennia | B5: HDFC Bank | C5: 200000 | D5: 45000 | E5: 2250 | F5: 2026-07-08 | G5: =IF(C5>0,D5/C5,0) | H5: suman123
A6: SBI SimplyCLICK | B6: SBI Card | C6: 100000 | D6: 12000 | E6: 600 | F6: 2026-07-13 | G6: =IF(C6>0,D6/C6,0) | H6: suman123
A7: TOTAL | C7: =SUM(C5:C6) | D7: =SUM(D5:D6) | E7: =SUM(E5:E6)

Sheet 🔄 Subscriptions
A1: WealthPilot 360 — Subscription Tracker
A2: OTT, apps, tools & all recurring subscriptions
A4: Service Name | B4: Category | C4: Amount (₹) | D4: Cycle | E4: Renewal Date | F4: Monthly Cost (₹) | G4: User ID | H4: Notes
A5: Netflix | B5: OTT/Streaming | C5: 649 | D5: Monthly | E5: 2026-07-18 | F5: =IF(D5="Monthly",C5,IF(D5="Yearly",C5/12,IF(D5="Quarterly",C5/3,C5))) | G5: suman123
A6: Amazon Prime | B6: OTT/Streaming | C6: 1499 | D6: Yearly | E6: 2026-09-26 | F6: =IF(D6="Monthly",C6,IF(D6="Yearly",C6/12,IF(D6="Quarterly",C6/3,C6))) | G6: suman123
A7: ChatGPT Plus | B7: AI Tools | C7: 1600 | D7: Monthly | E7: 2026-07-23 | F7: =IF(D7="Monthly",C7,IF(D7="Yearly",C7/12,IF(D7="Quarterly",C7/3,C7))) | G7: suman123
A8: YouTube Premium | B8: OTT/Streaming | C8: 189 | D8: Monthly | E8: 2026-07-16 | F8: =IF(D8="Monthly",C8,IF(D8="Yearly",C8/12,IF(D8="Quarterly",C8/3,C8))) | G8: suman123
A9: TOTAL / MONTH | F9: =SUM(F5:F8)

Sheet 💵 Transactions
A1: WealthPilot 360 — Income & Expense Ledger
A2: Every transaction — salary, grocery, freelance, shopping etc.
A4: Date | B4: Description | C4: Category | D4: Type | E4: Amount (₹) | F4: Month | G4: User ID | H4: Notes
A5: 2026-06-28 | B5: Monthly Salary | C5: Salary | D5: Income | E5: 95000 | F5: 2026-06 | G5: suman123
A6: 2026-06-28 | B6: Grocery Shopping | C6: Food | D6: Expense | E6: 8500 | F6: 2026-06 | G6: suman123
A7: 2026-06-28 | B7: Freelance Project | C7: Business | D7: Income | E7: 25000 | F7: 2026-06 | G7: suman123
A8: 2026-06-28 | B8: Dining Out | C8: Food | D8: Expense | E8: 3200 | F8: 2026-06 | G8: suman123
A9: 2026-06-28 | B9: Amazon Shopping | C9: Shopping | D9: Expense | E9: 4500 | F9: 2026-06 | G9: suman123
A10: TOTAL INCOME | E10: =SUMIF(D5:D9,"Income",E5:E9)
A11: TOTAL EXPENSES | E11: =SUMIF(D5:D9,"Expense",E5:E9)
A12: NET SAVINGS | E12: =E10-E11

Sheet 🎯 Goals
A1: WealthPilot 360 — Financial Goals
A2: Car, education, emergency fund & life goals tracker
A4: Goal Name | B4: Category | C4: Target Amount (₹) | D4: Saved So Far (₹) | E4: Remaining (₹) | F4: Progress (%) | G4: Target Date | H4: Days Left | I4: User ID
A5: Buy New Car | B5: Car | C5: 1500000 | D5: 280000 | E5: =C5-D5 | F5: =IF(C5>0,D5/C5,0) | G5: 2028-06-28 | H5: =IF(G5<>"",G5-TODAY(),"") | I5: suman123
A6: Children Education | B6: Education | C6: 3000000 | D6: 450000 | E6: =C6-D6 | F6: =IF(C6>0,D6/C6,0) | G6: 2034-06-28 | H6: =IF(G6<>"",G6-TODAY(),"") | I6: suman123
A7: Emergency Fund | B7: Emergency Fund | C7: 600000 | D7: 200000 | E7: =C7-D7 | F7: =IF(C7>0,D7/C7,0) | G7: 2027-06-28 | H7: =IF(G7<>"",G7-TODAY(),"") | I7: suman123

Sheet 📁 Documents
A1: WealthPilot 360 — Document Vault
A2: Passport, PAN, Aadhaar, Driving Licence & important docs
A4: Document Name | B4: Type | C4: Number / ID | D4: Expiry Date | E4: Days to Expiry | F4: Storage Location | G4: User ID | H4: Notes
A5: Passport | B5: Passport | C5: A1234567 | D5: 2027-08-02 | E5: =IF(D5<>"",D5-TODAY(),"") | F5: Home Safe | G5: suman123
A6: PAN Card | B6: PAN Card | C6: ABCDE1234F | E6: =IF(D6<>"",D6-TODAY(),"") | F6: Wallet | G6: suman123
A7: Aadhaar Card | B7: Aadhaar Card | C7: XXXX-XXXX-4567 | E7: =IF(D7<>"",D7-TODAY(),"") | F7: Wallet | G7: suman123
A8: Driving Licence | B8: Driving Licence | C8: WB-0120190012345 | D8: 2028-09-05 | E8: =IF(D8<>"",D8-TODAY(),"") | F8: Wallet | G8: suman123

Sheet 👨‍👩‍👧‍👦 Family
A1: WealthPilot 360 — Family Office
A2: Family members & their financial overview
A4: Member Name | B4: Relation | C4: Date of Birth | D4: Age | E4: PAN | F4: Aadhaar (last 4) | G4: Primary User ID | H4: Notes
A5: Suman | B5: Self | G5: suman123
A6: Spouse | B6: Spouse | G6: suman123
A7: Father | B7: Father | G7: suman123
A8: Mother | B8: Mother | G8: suman123

Sheet 📊 Budget
A1: WealthPilot 360 — Budget Planner
A2: Monthly budget vs actual spending by category
A4: Category | B4: Budget Amount (₹) | C4: Actual Spent (₹) | D4: Remaining (₹) | E4: Used (%) | F4: Status | G4: User ID
A5: Food | B5: 12000 | C5: 0 | D5: =B5-C5 | E5: =IF(B5>0,C5/B5,0) | F5: =IF(E5>1,"⚠️ Over Budget",IF(E5>0.8,"🔶 Near Limit","✅ On Track")) | G5: suman123
A6: Shopping | B6: 8000 | C6: 0 | D6: =B6-C6 | E6: =IF(B6>0,C6/B6,0) | F6: =IF(E6>1,"⚠️ Over Budget",IF(E6>0.8,"🔶 Near Limit","✅ On Track")) | G6: suman123
A7: Entertainment | B7: 3000 | C7: 0 | D7: =B7-C7 | E7: =IF(B7>0,C7/B7,0) | F7: =IF(E7>1,"⚠️ Over Budget",IF(E7>0.8,"🔶 Near Limit","✅ On Track")) | G7: suman123
A8: Travel | B8: 5000 | C8: 0 | D8: =B8-C8 | E8: =IF(B8>0,C8/B8,0) | F8: =IF(E8>1,"⚠️ Over Budget",IF(E8>0.8,"🔶 Near Limit","✅ On Track")) | G8: suman123
